reg_query.py
reg_query-0.1.1.dist-info/LICENSE
reg_query-0.1.1.dist-info/METADATA
reg_query-0.1.1.dist-info/WHEEL
reg_query-0.1.1.dist-info/RECORD
