Metadata-Version: 2.1
Name: reg_query
Version: 0.1.1
Summary: `reg_query` is a Python library for querying the Windows Registry to find specified values and keys efficiently.
Home-page: https://github.com/th-yoo/reg_query
License: MIT
Keywords: registry,win32
Author: th yoo
Author-email: taihyungyoo@gmail.com
Requires-Python: >=3.9,<4.0
Classifier: License :: OSI Approved :: MIT License
Classifier: Programming Language :: Python :: 3
Classifier: Programming Language :: Python :: 3.9
Classifier: Programming Language :: Python :: 3.10
Classifier: Programming Language :: Python :: 3.11
Classifier: Programming Language :: Python :: 3.12
